{
    "user_id":10000000000000,
    "customer_dealerName":"Max Headroom",
    "customer_title":"",
    "user_salutation":0,
    "user_firstName":"Max",
    "user_surName":"Mustermann",
    "user_mobile":"+49123/4567890",
    "customer_phone":"+49456/78901234",
    "customer_fax":"+49456/789012555",
    "user_street":"Musterstrasse",
    "user_houseNumber":"123a",
    "user_additionalAdress":"Rückgebäude",
    "user_zip":12345,
    "user_residence":"Musterstadt",
    "user_country":"Musterland",
    "user_sex":"male",
    "user_birthDate":"1965-07-31",
    "user_regDate":"2021-10-27 22:18:23",
    "customer_wallet":123.45,
    "user_email":"muster@mustermail.de",
    "customer_contractPower":true,
    "customer_contractGas":false,
    "customer_contractDsl":false,
    "customer_contractMobile":false,
    "customer_contractSolar":false,
    "customer_recommendation":1,
    "customer_openTicket":false
}